accessnode/__init__.py
accessnode/accessnode.py
accessnode/py.typed
accessnode/api/__init__.py
accessnode/api/main_api.py
accessnode/api/routers/__init__.py
accessnode/api/routers/provisioning.py
accessnode/api/routers/user.py
accessnode/api/routers/user_secure.py
accessnode/auth/__init__.py
accessnode/auth/audit.py
accessnode/auth/production.py
accessnode/auth/router.py
accessnode/auth/schemas.py
accessnode/auth/security.py
accessnode/caching/__init__.py
accessnode/caching/cache_database_handler.py
accessnode/caching/cache_manager.py
accessnode/caching/cache_strategy.py
accessnode/caching/memory.py
accessnode/caching/redis_cache.py
accessnode/core/__init__.py
accessnode/core/base.py
accessnode/core/config.py
accessnode/core/decorators.py
accessnode/core/exceptions.py
accessnode/core/types.py
accessnode/core/validation.py
accessnode/database/__init__.py
accessnode/database/base.py
accessnode/database/pool.py
accessnode/database/transaction.py
accessnode/database/types.py
accessnode/database/utils.py
accessnode/database/databases/mongodb.py
accessnode/database/databases/mysql.py
accessnode/database/databases/postgres.py
accessnode/database/databases/sqlite.py
accessnode/models/__init__.py
accessnode/models/base.py
accessnode/models/fields.py
accessnode/models/relations.py
accessnode/plugins/__init__.py
accessnode/plugins/base_plugin.py
accessnode/plugins/plugin_manager.py
accessnode/query/__init__.py
accessnode/query/base_query.py
accessnode/query/builder.py
accessnode/query/compiler.py
accessnode/query/filters.py
accessnode/query/types.py
accessnode/real_time/__init__.py
accessnode/real_time/cdc_manager.py
accessnode/real_time/subscription.py
accessnode/schema_manager/__init__.py
accessnode/schema_manager/schema_creator.py
accessnode/schema_manager/schema_manager.py
accessnode/schema_manager/schema_migration.py
accessnode/schema_manager/schema_updater.py
accessnode/schema_manager/schema_validator.py
accessnode/services/database_provisioner.py
accessnode-0.1.1.dist-info/METADATA
accessnode-0.1.1.dist-info/WHEEL
accessnode-0.1.1.dist-info/licenses/LICENSE
accessnode-0.1.1.dist-info/RECORD
