Metadata-Version: 2.4
Name: accessnode
Version: 0.1.1
Summary: A secure and flexible database management system
Project-URL: Homepage, https://github.com/accessnode/accessnode
Project-URL: Documentation, https://accessnode.dev/docs
Project-URL: Repository, https://github.com/accessnode/accessnode.git
Project-URL: Issues, https://github.com/accessnode/accessnode/issues
Author-email: AccessNode Team <team@accessnode.dev>
License-Expression: MIT
License-File: LICENSE
Keywords: database,fastapi,management,mongodb,mysql,postgresql
Classifier: Development Status :: 4 - Beta
Classifier: Intended Audience :: Developers
Classifier: License :: OSI Approved :: MIT License
Classifier: Programming Language :: Python :: 3
Classifier: Programming Language :: Python :: 3.8
Classifier: Programming Language :: Python :: 3.9
Classifier: Programming Language :: Python :: 3.10
Classifier: Programming Language :: Python :: 3.11
Requires-Python: >=3.8
Requires-Dist: aiomysql>=0.2.0
Requires-Dist: asyncpg>=0.29.0
Requires-Dist: cryptography>=41.0.5
Requires-Dist: databases>=0.8.0
Requires-Dist: fastapi>=0.104.1
Requires-Dist: passlib>=1.7.4
Requires-Dist: pydantic>=2.5.1
Requires-Dist: pymongo>=4.6.0
Requires-Dist: pymysql>=1.1.0
Requires-Dist: python-jose>=3.3.0
Requires-Dist: python-multipart>=0.0.6
Requires-Dist: sqlalchemy>=2.0.23
Requires-Dist: uvicorn>=0.24.0
Provides-Extra: build
Requires-Dist: build>=0.10.0; extra == 'build'
Requires-Dist: twine>=4.0.2; extra == 'build'
Provides-Extra: dev
Requires-Dist: black>=23.11.0; extra == 'dev'
Requires-Dist: httpx>=0.25.1; extra == 'dev'
Requires-Dist: isort>=5.12.0; extra == 'dev'
Requires-Dist: mypy>=1.7.0; extra == 'dev'
Requires-Dist: pytest-asyncio>=0.21.1; extra == 'dev'
Requires-Dist: pytest>=7.4.3; extra == 'dev'
Requires-Dist: ruff>=0.1.5; extra == 'dev'
